MANIFEST.in
README.md
setup.py
excursion/__init__.py
excursion/commandline.py
excursion/utils.py
excursion.egg-info/PKG-INFO
excursion.egg-info/SOURCES.txt
excursion.egg-info/dependency_links.txt
excursion.egg-info/entry_points.txt
excursion.egg-info/requires.txt
excursion.egg-info/top_level.txt
excursion/diagnosis/__init__.py
excursion/diagnosis/samplers.py
excursion/optimize/__init__.py
excursion/optimize/core.py
excursion/plotting/__init__.py
excursion/plotting/threedim.py
excursion/plotting/twodim.py
excursion/testcases/__init__.py
excursion/testcases/checkmate.py
excursion/testcases/darkhiggs.py
excursion/testcases/darkhiggs_2d.py
excursion/testcases/dummy_checkmate.py
excursion/testcases/fast.py
excursion/testcases/fast3d.py
excursion/testcases/toy3d_foursheets.py
excursion/testcases/toy3d_quartsphere.py